{
  "parent": "rpg_classes:obtain_healing_rune",
  "display": {
    "icon": {
      "item": "paladins:wooden_great_hammer"
    },
    "title": {
      "translate": "advancements.loot_n_explore.paladins_join.title"
    },
    "description": {
      "translate": "advancements.loot_n_explore.paladins_join.description"
    },
    "frame": "challenge",
    "show_toast": true,
    "announce_to_chat": true,
    "hidden": false
  },
  "criteria": {
    "requirement": {
      "conditions": {
        "location": [
          {
            "condition": "minecraft:location_check",
            "predicate": {
              "block": {
                "blocks": [
                  "minecraft:lectern"
                ]
              }
            }
          },
          {
            "condition": "minecraft:entity_properties",
            "entity": "this",
            "predicate": {
              "location": {
                "structure": "loot_n_explore:paladins_recruiting"
              }
            }
          }
        ]
      },
      "trigger": "minecraft:item_used_on_block"
    }
  },
  "rewards": {
    "experience": 10
  },
  "sends_telemetry_event": false
}
