{
  "parent": "rpg_classes:obtain_healing_rune",
  "criteria": {
    "paladins_shrine": {
      "conditions": {
        "player": [
          {
            "condition": "minecraft:entity_properties",
            "entity": "this",
            "predicate": {
              "location": {
                "structure": "loot_n_explore:paladins_shrine"
              }
            }
          }
        ]
      },
      "trigger": "minecraft:location"
    }
  },
  "display": {
    "announce_to_chat": true,
    "hidden": false,
    "show_toast": true,
    "frame": "challenge",
    "icon": {
      "item": "minecraft:bell"
    },
    "title": {
      "translate": "advancements.loot_n_explore.paladins_shrine.title"
    },
    "description": {
      "translate": "advancements.loot_n_explore.paladins_shrine.description"
    }
  },
  "requirements": [
    [
      "paladins_shrine"
    ]
  ],
  "rewards": {
    "experience": 10
  },
  "sends_telemetry_event": false
}
